Workbook

Sheet Valuation
A1: Inventory valuation — KITCHEN — 2026-08-01
A2: Source counts: Prep count July 31 (2026-07-31) + Full Count End of Month (2026-08-01). Each item is shown at its most recent physical count. Prices are the corrected prices in the system as at 2026-08-11.
A4: Item | B4: Category | C4: Storage area | D4: Supplier | E4: Quantity basis | F4: Counted on | G4: Qty counted | H4: Count unit | I4: Qty (base) | J4: Base unit | K4: Price at count ($/base) | L4: Price now ($/base) | M4: Value at count | N4: Value at current prices | O4: Change | P4: Price now (readable) | Q4: Per | R4: Pack format
A5: Baguette | B5: BREAD | C5: FREEZER | E5: Physically counted 2026-08-01 | F5: 2026-08-01 | G5: 0 | H5: each | I5: 0 | J5: each | K5: 3.135 | L5: 3.135 | M5: =I5*K5 | N5: =I5*L5 | O5: =N5-M5 | P5: 3.135 | Q5: each | R5: 20 case → 1 each
A6: Brioche Unsliced | B6: BREAD | E6: Physically counted 2026-08-01 | F6: 2026-08-01 | G6: 18 | H6: each | I6: 18 | J6: each | K6: 10.03 | L6: 10.03 | M6: =I6*K6 | N6: =I6*L6 | O6: =N6-M6 | P6: 10.03 | Q6: each | R6: 8 cs
A7: BUN BURGER SWT POTATO JAL CHDR | B7: BREAD | D7: Sysco | E7: Physically counted 2026-08-01 | F7: 2026-08-01 | G7: 2 | H7: case | I7: 10656 | J7: g | K7: 0.011991366 | L7: 0.011991366 | M7: =I7*K7 | N7: =I7*L7 | O7: =N7-M7 | P7: 11.991366 | Q7: kg | R7: 72 case → 74 each
A8: Burger Bun Sliced | B8: BREAD | E8: Physically counted 2026-08-01 | F8: 2026-08-01 | G8: 3 | H8: case | I8: 216 | J8: each | K8: 0.81138889 | L8: 0.81138889 | M8: =I8*K8 | N8: =I8*L8 | O8: =N8-M8 | P8: 0.81138889 | Q8: each | R8: 8 case → 9 each
A9: Croissant Plain | B9: BREAD | E9: Physically counted 2026-08-01 | F9: 2026-08-01 | G9: 120 | H9: each | I9: 120 | J9: each | K9: 2.7 | L9: 2.7 | M9: =I9*K9 | N9: =I9*L9 | O9: =N9-M9 | P9: 2.7 | Q9: each | R9: 1 each → 1 each
A10: cruffins | B10: BREAD | E10: Physically counted 2026-08-01 | F10: 2026-08-01 | G10: 60 | H10: each | I10: 60 | J10: each | K10: 2.6 | L10: 2.6 | M10: =I10*K10 | N10: =I10*L10 | O10: =N10-M10 | P10: 2.6 | Q10: each | R10: 1 each → 1 each
A11: ENGLISH MUFFIN GF 4PK | B11: BREAD | D11: Snow Cap | E11: Physically counted 2026-08-01 | F11: 2026-08-01 | G11: 16.3 | H11: pack | I11: 65.2 | J11: each | K11: 1.6879167 | L11: 1.6879167 | M11: =I11*K11 | N11: =I11*L11 | O11: =N11-M11 | P11: 1.6879167 | Q11: each | R11: 6 case → 4 pack
A12: GF Brioche Bun | B12: BREAD | E12: Physically counted 2026-08-01 | F12: 2026-08-01 | G12: 14 | H12: pack | I12: 84 | J12: each | K12: 1.6879167 | L12: 1.6879167 | M12: =I12*K12 | N12: =I12*L12 | O12: =N12-M12 | P12: 1.6879167 | Q12: each | R12: 4 case → 6 pack
A13: GF ENGLISH MUFFIN | B13: BREAD | D13: Sysco | E13: Physically counted 2026-08-01 | F13: 2026-08-01 | G13: 0 | H13: pack | I13: 0 | J13: each | K13: 1.6879167 | L13: 1.6879167 | M13: =I13*K13 | N13: =I13*L13 | O13: =N13-M13 | P13: 1.6879167 | Q13: each | R13: 4 case → 6 pack
A14: GF SOFT WHITE LOAF | B14: BREAD | E14: Physically counted 2026-08-01 | F14: 2026-08-01 | G14: 12 | H14: each | I14: 5760 | J14: g | K14: 0.0140625 | L14: 0.0140625 | M14: =I14*K14 | N14: =I14*L14 | O14: =N14-M14 | P14: 14.0625 | Q14: kg | R14: 4 case → 480 each
A15: Naan Bread Round 8 in | B15: BREAD | D15: Sysco | E15: Physically counted 2026-08-01 | F15: 2026-08-01 | G15: 0 | H15: pack | I15: 0 | J15: each | K15: 0.88854167 | L15: 0.88854167 | M15: =I15*K15 | N15: =I15*L15 | O15: =N15-M15 | P15: 0.88854167 | Q15: each | R15: 6 case → 8 pack
A16: Pain au Chocolate | B16: BREAD | C16: FREEZER | E16: Physically counted 2026-08-01 | F16: 2026-08-01 | G16: 66 | H16: each | I16: 66 | J16: each | K16: 2.9 | L16: 2.9 | M16: =I16*K16 | N16: =I16*L16 | O16: =N16-M16 | P16: 2.9 | Q16: each | R16: 1 each → 1 each
A17: Pastry shell chocolate | B17: BREAD | C17: CATERING | E17: Physically counted 2026-08-01 | F17: 2026-08-01 | G17: 0 | H17: each | I17: 0 | J17: each | K17: 2.0983333 | L17: 2.0983333 | M17: =I17*K17 | N17: =I17*L17 | O17: =N17-M17 | P17: 2.0983333 | Q17: each | R17: 60 case
A18: Pita Bread | B18: BREAD | E18: Physically counted 2026-08-01 | F18: 2026-08-01 | G18: 35 | H18: pack | I18: 210 | J18: each | K18: 0.27402778 | L18: 0.27402778 | M18: =I18*K18 | N18: =I18*L18 | O18: =N18-M18 | P18: 0.27402778 | Q18: each | R18: 24 case → 6 pack
A19: Pizza Margherita RETAIL 12 x 615g WOOZA | B19: BREAD | D19: Legends Haul | E19: Physically counted 2026-08-01 | F19: 2026-08-01 | G19: 0 | H19: each | I19: 0 | J19: g | K19: 0.021680217 | L19: 0.021680217 | M19: =I19*K19 | N19: =I19*L19 | O19: =N19-M19 | P19: 21.680217 | Q19: kg | R19: 12 case → 615 each
A20: Pizza Pepperoni RETAIL 12 x 600g WOOZA | B20: BREAD | D20: Legends Haul | E20: Physically counted 2026-08-01 | F20: 2026-08-01 | G20: 0 | H20: each | I20: 0 | J20: g | K20: 0.022222222 | L20: 0.022222222 | M20: =I20*K20 | N20: =I20*L20 | O20: =N20-M20 | P20: 22.222222 | Q20: kg | R20: 12 case → 600 each
A21: PUFF PASTRY CROISSANT | B21: BREAD | E21: Physically counted 2026-08-01 | F21: 2026-08-01 | G21: 10 | H21: each | I21: 10 | J21: each | K21: 18.236 | L21: 18.236 | M21: =I21*K21 | N21: =I21*L21 | O21: =N21-M21 | P21: 18.236 | Q21: each | R21: 10 case
A22: Spring roll wrappers | B22: BREAD | C22: FREEZER | E22: Physically counted 2026-08-01 | F22: 2026-08-01 | G22: 0 | H22: kg | I22: 0 | J22: g | K22: 0.012545455 | L22: 0.012545455 | M22: =I22*K22 | N22: =I22*L22 | O22: =N22-M22 | P22: 12.545455 | Q22: kg | R22: 1 each → 11000 each
A23: Yellow corn Tortillas | B23: BREAD | D23: Sysco | E23: Physically counted 2026-08-01 | F23: 2026-08-01 | G23: 11.5 | H23: pack | I23: 690 | J23: each | K23: 0.10713889 | L23: 0.10713889 | M23: =I23*K23 | N23: =I23*L23 | O23: =N23-M23 | P23: 0.10713889 | Q23: each | R23: 12 case → 60 pack
A24: DETERGENT POT/PAN MANUAL | B24: CHM | D24: Sysco | E24: Physically counted 2026-08-01 | F24: 2026-08-01 | G24: 2 | H24: each | I24: 1814.368 | J24: g | K24: 0.073028184 | L24: 0.073028184 | M24: =I24*K24 | N24: =I24*L24 | O24: =N24-M24 | P24: 73.028184 | Q24: kg | R24: 3 case → 907.184 each
A25: Butter | B25: DAIRY | C25: FRIDGE | E25: Physically counted 2026-08-01 | F25: 2026-08-01 | G25: 4.5 | H25: case | I25: 51075 | J25: g | K25: 0.015223789 | L25: 0.015223789 | M25: =I25*K25 | N25: =I25*L25 | O25: =N25-M25 | P25: 15.223789 | Q25: kg | R25: 25 case → 454 each
A26: Buttermilk | B26: DAIRY | C26: FRIDGE | E26: Physically counted 2026-08-01 | F26: 2026-08-01 | G26: 8 | H26: each | I26: 32000 | J26: ml | K26: 0.002755625 | L26: 0.002755625 | M26: =I26*K26 | N26: =I26*L26 | O26: =N26-M26 | P26: 2.755625 | Q26: L | R26: 4 case → 4000 each
A27: Cheddar smoked | B27: DAIRY | C27: FRIDGE | D27: Sysco | E27: Physically counted 2026-08-01 | F27: 2026-08-01 | G27: 9.4 | H27: kg | I27: 9400 | J27: g | K27: 0.03423 | L27: 0.03423 | M27: =I27*K27 | N27: =I27*L27 | O27: =N27-M27 | P27: 34.23 | Q27: kg | R27: 1000 case
A28: Cheddar whiite | B28: DAIRY | C28: FRIDGE | E28: Physically counted 2026-08-01 | F28: 2026-08-01 | G28: 5 | H28: kg | I28: 5000 | J28: g | K28: 0.019105727 | L28: 0.010698238 | M28: =I28*K28 | N28: =I28*L28 | O28: =N28-M28 | P28: 10.698238 | Q28: kg | R28: 2 case → 2270 each
A29: Cream cheese | B29: DAIRY | E29: Physically counted 2026-08-01 | F29: 2026-08-01 | G29: 1.5 | H29: kg | I29: 1500 | J29: g | K29: 0.015413333 | L29: 0.015413333 | M29: =I29*K29 | N29: =I29*L29 | O29: =N29-M29 | P29: 15.413333 | Q29: kg | R29: 6 case → 1500 each
A30: Cream whipped | B30: DAIRY | C30: FRIDGE | D30: Sysco | E30: Physically counted 2026-08-01 | F30: 2026-08-01 | G30: 16 | H30: each | I30: 15136 | J30: ml | K30: 0.0073506871 | L30: 0.0072482822 | M30: =I30*K30 | N30: =I30*L30 | O30: =N30-M30 | P30: 7.2482822 | Q30: L | R30: 16 case → 946 each
A31: Feta | B31: DAIRY | C31: FRIDGE | E31: Physically counted 2026-08-01 | F31: 2026-08-01 | G31: 2 | H31: case | I31: 6000 | J31: g | K31: 0.0174 | L31: 0.0174 | M31: =I31*K31 | N31: =I31*L31 | O31: =N31-M31 | P31: 17.4 | Q31: kg | R31: 1 case → 3000 each
A32: Free Run Eggs | B32: DAIRY | D32: Sysco | E32: Physically counted 2026-08-01 | F32: 2026-08-01 | G32: 19 | H32: case | I32: 3420 | J32: each | K32: 0.43333333 | L32: 0.43333333 | M32: =I32*K32 | N32: =I32*L32 | O32: =N32-M32 | P32: 0.43333333 | Q32: each | R32: 12 case → 15 pack → 1 each
A33: Goats Cheese | B33: DAIRY | C33: FRIDGE | D33: Sysco | E33: Physically counted 2026-08-01 | F33: 2026-08-01 | G33: 1 | H33: case | I33: 2000 | J33: g | K33: 0.029815 | L33: 0.029815 | M33: =I33*K33 | N33: =I33*L33 | O33: =N33-M33 | P33: 29.815 | Q33: kg | R33: 2 case → 1000 each
A34: Grana Padano | B34: DAIRY | C34: FRIDGE | D34: Sysco | E34: Physically counted 2026-08-01 | F34: 2026-08-01 | G34: 6.4 | H34: kg | I34: 6400 | J34: g | K34: 0.0293 | L34: 0.0293 | M34: =I34*K34 | N34: =I34*L34 | O34: =N34-M34 | P34: 29.3 | Q34: kg | R34: 1000 case
A35: Greek Style Yogurt | B35: DAIRY | C35: FRIDGE | D35: Sysco | E35: Physically counted 2026-08-01 | F35: 2026-08-01 | G35: 0 | H35: each | I35: 0 | J35: g | K35: 0.007565 | L35: 0.007565 | M35: =I35*K35 | N35: =I35*L35 | O35: =N35-M35 | P35: 7.565 | Q35: kg | R35: 1 each → 4000 each
A36: Halloumi | B36: DAIRY | C36: FRIDGE | D36: Sysco | E36: Physically counted 2026-08-01 | F36: 2026-08-01 | G36: 5 | H36: case | I36: 12500 | J36: g | K36: 0.033176 | L36: 0.033176 | M36: =I36*K36 | N36: =I36*L36 | O36: =N36-M36 | P36: 33.176 | Q36: kg | R36: 10 case → 250 each
A37: Havarti cheese | B37: DAIRY | C37: CATERING | D37: Sysco | E37: Physically counted 2026-08-01 | F37: 2026-08-01 | G37: 2.8 | H37: kg | I37: 2800 | J37: g | K37: 0.02186 | L37: 0.02186 | M37: =I37*K37 | N37: =I37*L37 | O37: =N37-M37 | P37: 21.86 | Q37: kg | R37: 3250 case
A38: Heavy Cream 35% | B38: DAIRY | D38: Snow Cap | E38: Physically counted 2026-08-01 | F38: 2026-08-01 | G38: 0 | H38: case | I38: 0 | J38: ml | K38: 0.00695375 | L38: 0.00695375 | M38: =I38*K38 | N38: =I38*L38 | O38: =N38-M38 | P38: 6.95375 | Q38: L | R38: 16 case → 1000 each
A39: Liquid Egg Yolk | B39: DAIRY | C39: FRIDGE | E39: Physically counted 2026-08-01 | F39: 2026-08-01 | G39: 13 | H39: kg | I39: 13000 | J39: g | K39: 0.008605 | L39: 0.008605 | M39: =I39*K39 | N39: =I39*L39 | O39: =N39-M39 | P39: 8.605 | Q39: kg | R39: 12 cs → 1000 kg
A40: Margerine Vegan | B40: DAIRY | C40: FRIDGE | E40: Physically counted 2026-08-01 | F40: 2026-08-01 | G40: 8 | H40: kg | I40: 8000 | J40: g | K40: 0.0073575 | L40: 0.0073575 | M40: =I40*K40 | N40: =I40*L40 | O40: =N40-M40 | P40: 7.3575 | Q40: kg | R40: 1 each → 8000 each
A41: Mascarpone | B41: DAIRY | C41: FRIDGE | D41: Sysco | E41: Physically counted 2026-08-01 | F41: 2026-08-01 | G41: 0 | H41: each | I41: 0 | J41: g | K41: 0.031417544 | L41: 0.031417544 | M41: =I41*K41 | N41: =I41*L41 | O41: =N41-M41 | P41: 31.417544 | Q41: kg | R41: 6 case → 475 each
A42: Milk Whole HOMOGENIZED | B42: DAIRY | C42: FRIDGE | D42: Snow Cap | E42: Physically counted 2026-08-01 | F42: 2026-08-01 | G42: 12 | H42: each | I42: 48000 | J42: ml | K42: 0.002219375 | L42: 0.002219375 | M42: =I42*K42 | N42: =I42*L42 | O42: =N42-M42 | P42: 2.219375 | Q42: L | R42: 4 case → 4000 each
A43: Provolone | B43: DAIRY | C43: FRIDGE | E43: Physically counted 2026-08-01 | F43: 2026-08-01 | G43: 0 | H43: kg | I43: 0 | J43: g | K43: 0.02308 | L43: 0.02308 | M43: =I43*K43 | N43: =I43*L43 | O43: =N43-M43 | P43: 23.08 | Q43: kg | R43: 1 each → 1000 each
A44: Ricotta | B44: DAIRY | C44: FRIDGE | D44: Sysco | E44: Physically counted 2026-08-01 | F44: 2026-08-01 | G44: 0 | H44: each | I44: 0 | J44: g | K44: 0.0144625 | L44: 0.0144625 | M44: =I44*K44 | N44: =I44*L44 | O44: =N44-M44 | P44: 14.4625 | Q44: kg | R44: 1 each → 4000 each
A45: Sour Cream | B45: DAIRY | D45: Sysco | E45: Physically counted 2026-08-01 | F45: 2026-08-01 | G45: 1 | H45: case | I45: 4000 | J45: ml | K45: 0.00774 | L45: 0.00774 | M45: =I45*K45 | N45: =I45*L45 | O45: =N45-M45 | P45: 7.74 | Q45: L | R45: 1 case → 4000 each
A46: Activated Carbon | B46: DRY | C46: PREP-AREA | E46: Physically counted 2026-08-01 | F46: 2026-08-01 | G46: 0.374 | H46: kg | I46: 374 | J46: g | K46: 0.13911894 | L46: 0.13911894 | M46: =I46*K46 | N46: =I46*L46 | O46: =N46-M46 | P46: 139.11894 | Q46: kg | R46: 1 each → 454 each
A47: agar agar | B47: DRY | C47: PREP-AREA | E47: Physically counted 2026-08-01 | F47: 2026-08-01 | G47: 154 | H47: g | I47: 154 | J47: g | K47: 0.12368 | L47: 0.12368 | M47: =I47*K47 | N47: =I47*L47 | O47: =N47-M47 | P47: 123.68 | Q47: kg | R47: 1 each → 500 each
A48: All Purpose Flour | B48: DRY | E48: Physically counted 2026-08-01 | F48: 2026-08-01 | G48: 6.5 | H48: case | I48: 130000 | J48: g | K48: 0.002752 | L48: 0.002752 | M48: =I48*K48 | N48: =I48*L48 | O48: =N48-M48 | P48: 2.752 | Q48: kg | R48: 1 case → 20000 each
A49: Allspice | B49: DRY | C49: PREP-AREA | E49: Physically counted 2026-08-01 | F49: 2026-08-01 | G49: 0.7 | H49: kg | I49: 700 | J49: g | K49: 0.02926 | L49: 0.02926 | M49: =I49*K49 | N49: =I49*L49 | O49: =N49-M49 | P49: 29.26 | Q49: kg | R49: 1 each → 1000 each
A50: Almond flavor | B50: DRY | C50: SATELITE | E50: Physically counted 2026-08-01 | F50: 2026-08-01 | G50: 0.5 | H50: l | I50: 500 | J50: ml | K50: 0.01458 | L50: 0.01458 | M50: =I50*K50 | N50: =I50*L50 | O50: =N50-M50 | P50: 14.58 | Q50: L | R50: 1 each → 1000 each
A51: Almond meal | B51: DRY | C51: PREP-AREA | E51: Physically counted 2026-08-01 | F51: 2026-08-01 | G51: 0 | H51: each | I51: 0 | J51: g | K51: 0.016134 | L51: 0.016134 | M51: =I51*K51 | N51: =I51*L51 | O51: =N51-M51 | P51: 16.134 | Q51: kg | R51: 1 each → 5000 each
A52: Almond slices | B52: DRY | C52: SATELITE | D52: Sysco | E52: Skipped — expected qty at 2026-08-01 | F52: 2026-08-01 | G52: 1.8 | H52: kg | I52: 1800 | J52: g | K52: 0.04894 | L52: 0.04894 | M52: =I52*K52 | N52: =I52*L52 | O52: =N52-M52 | P52: 48.94 | Q52: kg | R52: 3 case → 1000 each
A53: Ancho paste | B53: DRY | C53: FREEZER | E53: Physically counted 2026-08-01 | F53: 2026-08-01 | G53: 0 | H53: each | I53: 0 | J53: g | K53: 0.047601626 | L53: 0.047601626 | M53: =I53*K53 | N53: =I53*L53 | O53: =N53-M53 | P53: 47.601626 | Q53: kg | R53: 6 case → 410 each
A54: Anis Seed Whole | B54: DRY | C54: PREP-AREA | D54: Snow Cap | E54: Physically counted 2026-08-01 | F54: 2026-08-01 | G54: 1.75 | H54: kg | I54: 1750 | J54: g | K54: 0.01859 | L54: 0.01859 | M54: =I54*K54 | N54: =I54*L54 | O54: =N54-M54 | P54: 18.59 | Q54: kg | R54: 2000 case
A55: Apple mustard | B55: DRY | E55: Physically counted 2026-08-01 | F55: 2026-08-01 | G55: 0 | H55: g | I55: 0 | J55: g | K55: 0 | L55: 0 | M55: =I55*K55 | N55: =I55*L55 | O55: =N55-M55 | P55: 0 | Q55: kg | R55: 1 each → 1 each
A56: ascorbic acid | B56: DRY | C56: PREP-AREA | E56: Physically counted 2026-08-01 | F56: 2026-08-01 | G56: 0 | H56: kg | I56: 0 | J56: g | K56: 0.049933921 | L56: 0.049933921 | M56: =I56*K56 | N56: =I56*L56 | O56: =N56-M56 | P56: 49.933921 | Q56: kg | R56: 1 each → 454 each
A57: Baking Powder | B57: DRY | C57: PREP-AREA | D57: Sysco | E57: Physically counted 2026-08-01 | F57: 2026-08-01 | G57: 5 | H57: kg | I57: 5000 | J57: g | K57: 0.015216667 | L57: 0.0056415 | M57: =I57*K57 | N57: =I57*L57 | O57: =N57-M57 | P57: 5.6415 | Q57: kg | R57: 20000 each
A58: Baking Soda | B58: DRY | C58: PREP-AREA | E58: Physically counted 2026-08-01 | F58: 2026-08-01 | G58: 0.765 | H58: kg | I58: 765 | J58: g | K58: 0.00375 | L58: 0.00375 | M58: =I58*K58 | N58: =I58*L58 | O58: =N58-M58 | P58: 3.75 | Q58: kg | R58: 1 each → 5000 each
A59: Barley | B59: DRY | C59: SATELITE | E59: Physically counted 2026-08-01 | F59: 2026-08-01 | G59: 0 | H59: kg | I59: 0 | J59: g | K59: 0.0024095 | L59: 0.0024095 | M59: =I59*K59 | N59: =I59*L59 | O59: =N59-M59 | P59: 2.4095 | Q59: kg | R59: 1 each → 20000 each
A60: Bay Leaves | B60: DRY | C60: PREP-AREA | E60: Physically counted 2026-08-01 | F60: 2026-08-01 | G60: 1 | H60: each | I60: 500 | J60: g | K60: 0.04864 | L60: 0.04864 | M60: =I60*K60 | N60: =I60*L60 | O60: =N60-M60 | P60: 48.64 | Q60: kg | R60: 1 each → 500 each
A61: Beans Dry Black | B61: DRY | C61: SATELITE | D61: Sysco | E61: Physically counted 2026-08-01 | F61: 2026-08-01 | G61: 2 | H61: case | I61: 20000 | J61: g | K61: 0.003548 | L61: 0.003548 | M61: =I61*K61 | N61: =I61*L61 | O61: =N61-M61 | P61: 3.548 | Q61: kg | R61: 1 case → 10000 each
A62: Beans Dry pinto | B62: DRY | C62: SATELITE | D62: Sysco | E62: Physically counted 2026-08-01 | F62: 2026-08-01 | G62: 0 | H62: kg | I62: 0 | J62: g | K62: 0.0039935 | L62: 0.0039935 | M62: =I62*K62 | N62: =I62*L62 | O62: =N62-M62 | P62: 3.9935 | Q62: kg | R62: 1 case → 20000 each
A63: Black caraway seeds | B63: DRY | E63: Physically counted 2026-08-01 | F63: 2026-08-01 | G63: 0 | H63: kg | I63: 0 | J63: g | K63: 0.030549451 | L63: 0.030549451 | M63: =I63*K63 | N63: =I63*L63 | O63: =N63-M63 | P63: 30.549451 | Q63: kg | R63: 1 each → 455 each
A64: black garlic | B64: DRY | C64: CATERING | E64: Physically counted 2026-08-01 | F64: 2026-08-01 | G64: 0.35 | H64: pack | I64: 87.5 | J64: g | K64: 0.12604 | L64: 0.12604 | M64: =I64*K64 | N64: =I64*L64 | O64: =N64-M64 | P64: 126.04 | Q64: kg | R64: 1 pack → 250 each
A65: Black Peppercorns | B65: DRY | C65: PREP-AREA | E65: Physically counted 2026-08-01 | F65: 2026-08-01 | G65: 2.7 | H65: kg | I65: 2700 | J65: g | K65: 0.01988 | L65: 0.01988 | M65: =I65*K65 | N65: =I65*L65 | O65: =N65-M65 | P65: 19.88 | Q65: kg | R65: 1 each → 2500 each
A66: black seasame seed | B66: DRY | C66: SATELITE | E66: Physically counted 2026-08-01 | F66: 2026-08-01 | G66: 0 | H66: each | I66: 0 | J66: g | K66: 0.01012 | L66: 0.01012 | M66: =I66*K66 | N66: =I66*L66 | O66: =N66-M66 | P66: 10.12 | Q66: kg | R66: 1 each → 3000 each
A67: Buckwheats | B67: DRY | C67: PREP-AREA | E67: Physically counted 2026-08-01 | F67: 2026-08-01 | G67: 15 | H67: kg | I67: 15000 | J67: g | K67: 0.0032989418 | L67: 0.0032989418 | M67: =I67*K67 | N67: =I67*L67 | O67: =N67-M67 | P67: 3.2989418 | Q67: kg | R67: 1 each → 22680 each
A68: CAPER SURFINE | B68: DRY | E68: Physically counted 2026-08-01 | F68: 2026-08-01 | G68: 1 | H68: each | I68: 1 | J68: each | K68: 91.38 | L68: 92.45 | M68: =I68*K68 | N68: =I68*L68 | O68: =N68-M68 | P68: 92.45 | Q68: each | R68: 1 case → 1 each
A69: Capers | B69: DRY | C69: PREP-AREA | D69: Sysco | E69: Physically counted 2026-08-01 | F69: 2026-08-01 | G69: 3 | H69: each | I69: 11340 | J69: ml | K69: 0.011646825 | L69: 0.011646825 | M69: =I69*K69 | N69: =I69*L69 | O69: =N69-M69 | P69: 11.646825 | Q69: L | R69: 2 case → 3780 each
A70: Caraway Seeds | B70: DRY | C70: PREP-AREA | E70: Physically counted 2026-08-01 | F70: 2026-08-01 | G70: 1 | H70: kg | I70: 1000 | J70: g | K70: 0.030549451 | L70: 0.030549451 | M70: =I70*K70 | N70: =I70*L70 | O70: =N70-M70 | P70: 30.549451 | Q70: kg | R70: 1 each → 455 each
A71: Cashews | B71: DRY | C71: PREP-AREA | D71: Sysco | E71: Physically counted 2026-08-01 | F71: 2026-08-01 | G71: 7.5 | H71: kg | I71: 7500 | J71: g | K71: 0.03302 | L71: 0.03302 | M71: =I71*K71 | N71: =I71*L71 | O71: =N71-M71 | P71: 33.02 | Q71: kg | R71: 2 case → 1500 each
A72: Chana Flour | B72: DRY | E72: Physically counted 2026-08-01 | F72: 2026-08-01 | G72: 0 | H72: kg | I72: 0 | J72: g | K72: 0.0036563696 | L72: 0.0036563696 | M72: =I72*K72 | N72: =I72*L72 | O72: =N72-M72 | P72: 3.6563696 | Q72: kg | R72: 1 each → 18143.68 each
A73: Chestnut flour | B73: DRY | E73: Physically counted 2026-08-01 | F73: 2026-08-01 | G73: 0.32 | H73: kg | I73: 320 | J73: g | K73: 0.0379 | L73: 0.0379 | M73: =I73*K73 | N73: =I73*L73 | O73: =N73-M73 | P73: 37.9 | Q73: kg | R73: 1 each → 1000 each
A74: Chia Seeds | B74: DRY | C74: PREP-AREA | E74: Physically counted 2026-08-01 | F74: 2026-08-01 | G74: 5 | H74: kg | I74: 5000 | J74: g | K74: 0.00947 | L74: 0.00947 | M74: =I74*K74 | N74: =I74*L74 | O74: =N74-M74 | P74: 9.47 | Q74: kg | R74: 1 each → 5000 each
A75: Chickpea dry | B75: DRY | D75: Sysco | E75: Physically counted 2026-08-01 | F75: 2026-08-01 | G75: 4.3 | H75: kg | I75: 4300 | J75: g | K75: 0.0045362832 | L75: 0.0045362832 | M75: =I75*K75 | N75: =I75*L75 | O75: =N75-M75 | P75: 4.5362832 | Q75: kg | R75: 1 each → 11300 each
A76: Chickpea Flour | B76: DRY | C76: PREP-AREA | E76: Physically counted 2026-08-01 | F76: 2026-08-01 | G76: 3 | H76: kg | I76: 3000 | J76: g | K76: 0.007579 | L76: 0.007579 | M76: =I76*K76 | N76: =I76*L76 | O76: =N76-M76 | P76: 7.579 | Q76: kg | R76: 1 each → 10000 each
A77: Chocolate white | B77: DRY | D77: Sysco | E77: Physically counted 2026-08-01 | F77: 2026-08-01 | G77: 7.5 | H77: kg | I77: 7500 | J77: g | K77: 0.027812 | L77: 0.027812 | M77: =I77*K77 | N77: =I77*L77 | O77: =N77-M77 | P77: 27.812 | Q77: kg | R77: 1 case → 5000 each
A78: Cinammon Ground | B78: DRY | E78: Physically counted 2026-08-01 | F78: 2026-08-01 | G78: 1.373 | H78: kg | I78: 1373 | J78: g | K78: 0.045145 | L78: 0.045145 | M78: =I78*K78 | N78: =I78*L78 | O78: =N78-M78 | P78: 45.145 | Q78: kg | R78: 1 each → 2000 each
A79: Cinnamon stick | B79: DRY | C79: PREP-AREA | D79: Sysco | E79: Physically counted 2026-08-01 | F79: 2026-08-01 | G79: 1 | H79: kg | I79: 1000 | J79: g | K79: 0.065511013 | L79: 0.065511013 | M79: =I79*K79 | N79: =I79*L79 | O79: =N79-M79 | P79: 65.511013 | Q79: kg | R79: 1 case → 2270 each
A80: citric acid | B80: DRY | C80: PREP-AREA | E80: Physically counted 2026-08-01 | F80: 2026-08-01 | G80: 0.06 | H80: kg | I80: 60 | J80: g | K80: 0.01636 | L80: 0.01636 | M80: =I80*K80 | N80: =I80*L80 | O80: =N80-M80 | P80: 16.36 | Q80: kg | R80: 1 each → 1000 each
A81: cocoa butter chips | B81: DRY | E81: Physically counted 2026-08-01 | F81: 2026-08-01 | G81: 0.6 | H81: kg | I81: 600 | J81: g | K81: 0.069686667 | L81: 0.069686667 | M81: =I81*K81 | N81: =I81*L81 | O81: =N81-M81 | P81: 69.686667 | Q81: kg | R81: 1 each → 3000 each
A82: Cocoa Nibs | B82: DRY | E82: Physically counted 2026-08-01 | F82: 2026-08-01 | G82: 0.4 | H82: pack | I82: 400 | J82: g | K82: 0.043 | L82: 0.043 | M82: =I82*K82 | N82: =I82*L82 | O82: =N82-M82 | P82: 43 | Q82: kg | R82: 1 pack → 1000 each
A83: Cocoa powder | B83: DRY | E83: Physically counted 2026-08-01 | F83: 2026-08-01 | G83: 0.388 | H83: kg | I83: 388 | J83: g | K83: 0.047253333 | L83: 0.047253333 | M83: =I83*K83 | N83: =I83*L83 | O83: =N83-M83 | P83: 47.253333 | Q83: kg | R83: 3 case → 1000 each
A84: Coconut fine repack | B84: DRY | C84: SATELITE | E84: Physically counted 2026-08-01 | F84: 2026-08-01 | G84: 1.846 | H84: kg | I84: 1846 | J84: g | K84: 0.009568 | L84: 0.009568 | M84: =I84*K84 | N84: =I84*L84 | O84: =N84-M84 | P84: 9.568 | Q84: kg | R84: 1 each → 5000 each
A85: coconut milk | B85: DRY | C85: PREP-AREA | D85: Sysco | E85: Physically counted 2026-08-01 | F85: 2026-08-01 | G85: 0 | H85: each | I85: 0 | J85: ml | K85: 0.0086875 | L85: 0.0070333216 | M85: =I85*K85 | N85: =I85*L85 | O85: =N85-M85 | P85: 7.0333216 | Q85: L | R85: 17046 case
A86: Coconut Oil | B86: DRY | C86: PREP-AREA | E86: Physically counted 2026-08-01 | F86: 2026-08-01 | G86: 18 | H86: kg | I86: 18000 | J86: g | K86: 0.011155333 | L86: 0.011155333 | M86: =I86*K86 | N86: =I86*L86 | O86: =N86-M86 | P86: 11.155333 | Q86: kg | R86: 1 each → 15000 each
A87: Coconut ribbons | B87: DRY | C87: PREP-AREA | E87: Physically counted 2026-08-01 | F87: 2026-08-01 | G87: 0 | H87: kg | I87: 0 | J87: g | K87: 0.011246 | L87: 0.011246 | M87: =I87*K87 | N87: =I87*L87 | O87: =N87-M87 | P87: 11.246 | Q87: kg | R87: 1 each → 5000 each
A88: Coffee Ground | B88: DRY | C88: PREP-AREA | E88: Physically counted 2026-08-01 | F88: 2026-08-01 | G88: 1 | H88: each | I88: 400 | J88: g | K88: 0.0495 | L88: 0.0495 | M88: =I88*K88 | N88: =I88*L88 | O88: =N88-M88 | P88: 49.5 | Q88: kg | R88: 1 case → 400 each
A89: Coriander ground | B89: DRY | C89: PREP-AREA | E89: Physically counted 2026-08-01 | F89: 2026-08-01 | G89: 0.38 | H89: kg | I89: 380 | J89: g | K89: 0.01079 | L89: 0.01079 | M89: =I89*K89 | N89: =I89*L89 | O89: =N89-M89 | P89: 10.79 | Q89: kg | R89: 1 each → 2000 each
A90: Coriander Seeds | B90: DRY | C90: PREP-AREA | E90: Physically counted 2026-08-01 | F90: 2026-08-01 | G90: 0.245 | H90: kg | I90: 245 | J90: g | K90: 0.025969163 | L90: 0.025969163 | M90: =I90*K90 | N90: =I90*L90 | O90: =N90-M90 | P90: 25.969163 | Q90: kg | R90: 1 each → 454 each
A91: Corn Starch | B91: DRY | C91: PREP-AREA | E91: Physically counted 2026-08-01 | F91: 2026-08-01 | G91: 14 | H91: kg | I91: 14000 | J91: g | K91: 0.00371 | L91: 0.00371 | M91: =I91*K91 | N91: =I91*L91 | O91: =N91-M91 | P91: 3.71 | Q91: kg | R91: 1 each → 5000 each
A92: Cracked coriander seed | B92: DRY | E92: Physically counted 2026-08-01 | F92: 2026-08-01 | G92: 200 | H92: g | I92: 200 | J92: g | K92: 0 | L92: 0 | M92: =I92*K92 | N92: =I92*L92 | O92: =N92-M92 | P92: 0 | Q92: kg | R92: 1 each → 1 each
A93: Cranberries Dried | B93: DRY | C93: PREP-AREA | D93: Sysco | E93: Physically counted 2026-08-01 | F93: 2026-08-01 | G93: 0 | H93: kg | I93: 0 | J93: g | K93: 0.012632353 | L93: 0.012632353 | M93: =I93*K93 | N93: =I93*L93 | O93: =N93-M93 | P93: 12.632353 | Q93: kg | R93: 2 case → 1360 each
A94: Crushed chili | B94: DRY | C94: PREP-AREA | E94: Physically counted 2026-08-01 | F94: 2026-08-01 | G94: 0.7 | H94: kg | I94: 700 | J94: g | K94: 0.01702 | L94: 0.01702 | M94: =I94*K94 | N94: =I94*L94 | O94: =N94-M94 | P94: 17.02 | Q94: kg | R94: 1 each → 1000 each
A95: Cumin | B95: DRY | C95: PREP-AREA | E95: Physically counted 2026-08-01 | F95: 2026-08-01 | G95: 1.5 | H95: kg | I95: 1500 | J95: g | K95: 0.02113 | L95: 0.02113 | M95: =I95*K95 | N95: =I95*L95 | O95: =N95-M95 | P95: 21.13 | Q95: kg | R95: 1000 case
A96: Cumin seeds | B96: DRY | C96: PREP-AREA | E96: Physically counted 2026-08-01 | F96: 2026-08-01 | G96: 0 | H96: kg | I96: 0 | J96: g | K96: 0.030484581 | L96: 0.030484581 | M96: =I96*K96 | N96: =I96*L96 | O96: =N96-M96 | P96: 30.484581 | Q96: kg | R96: 1 each → 454 each
A97: Curing salt PRAGUE | B97: DRY | C97: SATELITE | E97: Physically counted 2026-08-01 | F97: 2026-08-01 | G97: 10 | H97: g | I97: 10 | J97: g | K97: 0.01636 | L97: 0.01636 | M97: =I97*K97 | N97: =I97*L97 | O97: =N97-M97 | P97: 16.36 | Q97: kg | R97: 1 each → 1000 each
A98: Curry Powder | B98: DRY | C98: PREP-AREA | E98: Physically counted 2026-08-01 | F98: 2026-08-01 | G98: 3.15 | H98: kg | I98: 3150 | J98: g | K98: 0.011272 | L98: 0.011272 | M98: =I98*K98 | N98: =I98*L98 | O98: =N98-M98 | P98: 11.272 | Q98: kg | R98: 1 each → 2500 each
A99: dark rye flour | B99: DRY | C99: CATERING | E99: Physically counted 2026-08-01 | F99: 2026-08-01 | G99: 2.3 | H99: kg | I99: 2300 | J99: g | K99: 0.0013665 | L99: 0.0013665 | M99: =I99*K99 | N99: =I99*L99 | O99: =N99-M99 | P99: 1.3665 | Q99: kg | R99: 1 each → 20000 each
A100: Dried Diced Apricots | B100: DRY | C100: PREP-AREA | E100: Physically counted 2026-08-01 | F100: 2026-08-01 | G100: 0 | H100: kg | I100: 0 | J100: g | K100: 0.021 | L100: 0.021 | M100: =I100*K100 | N100: =I100*L100 | O100: =N100-M100 | P100: 21 | Q100: kg | R100: 1 each → 12500 each
A101: dried onion flakes | B101: DRY | C101: PREP-AREA | E101: Physically counted 2026-08-01 | F101: 2026-08-01 | G101: 0.8 | H101: kg | I101: 800 | J101: g | K101: 0.027367751 | L101: 0.027367751 | M101: =I101*K101 | N101: =I101*L101 | O101: =N101-M101 | P101: 27.367751 | Q101: kg | R101: 1 each → 1315.4168 each
...

Sheet Summary
A1: Summary — KITCHEN — 2026-08-01
A3: By category
A4: Category | B4: Lines | C4: Value at count | D4: Value at current prices | E4: Change
A5: BREAD | B5: =COUNTIF(Valuation!$B$5:$B$417,$A5) | C5: =SUMIF(Valuation!$B$5:$B$417,$A5,Valuation!$M$5:$M$417) | D5: =SUMIF(Valuation!$B$5:$B$417,$A5,Valuation!$N$5:$N$417) | E5: =D5-C5
A6: CHM | B6: =COUNTIF(Valuation!$B$5:$B$417,$A6) | C6: =SUMIF(Valuation!$B$5:$B$417,$A6,Valuation!$M$5:$M$417) | D6: =SUMIF(Valuation!$B$5:$B$417,$A6,Valuation!$N$5:$N$417) | E6: =D6-C6
A7: DAIRY | B7: =COUNTIF(Valuation!$B$5:$B$417,$A7) | C7: =SUMIF(Valuation!$B$5:$B$417,$A7,Valuation!$M$5:$M$417) | D7: =SUMIF(Valuation!$B$5:$B$417,$A7,Valuation!$N$5:$N$417) | E7: =D7-C7
A8: DRY | B8: =COUNTIF(Valuation!$B$5:$B$417,$A8) | C8: =SUMIF(Valuation!$B$5:$B$417,$A8,Valuation!$M$5:$M$417) | D8: =SUMIF(Valuation!$B$5:$B$417,$A8,Valuation!$N$5:$N$417) | E8: =D8-C8
A9: FISH | B9: =COUNTIF(Valuation!$B$5:$B$417,$A9) | C9: =SUMIF(Valuation!$B$5:$B$417,$A9,Valuation!$M$5:$M$417) | D9: =SUMIF(Valuation!$B$5:$B$417,$A9,Valuation!$N$5:$N$417) | E9: =D9-C9
A10: FROZEN | B10: =COUNTIF(Valuation!$B$5:$B$417,$A10) | C10: =SUMIF(Valuation!$B$5:$B$417,$A10,Valuation!$M$5:$M$417) | D10: =SUMIF(Valuation!$B$5:$B$417,$A10,Valuation!$N$5:$N$417) | E10: =D10-C10
A11: MEAT | B11: =COUNTIF(Valuation!$B$5:$B$417,$A11) | C11: =SUMIF(Valuation!$B$5:$B$417,$A11,Valuation!$M$5:$M$417) | D11: =SUMIF(Valuation!$B$5:$B$417,$A11,Valuation!$N$5:$N$417) | E11: =D11-C11
A12: PREPD | B12: =COUNTIF(Valuation!$B$5:$B$417,$A12) | C12: =SUMIF(Valuation!$B$5:$B$417,$A12,Valuation!$M$5:$M$417) | D12: =SUMIF(Valuation!$B$5:$B$417,$A12,Valuation!$N$5:$N$417) | E12: =D12-C12
A13: PROD | B13: =COUNTIF(Valuation!$B$5:$B$417,$A13) | C13: =SUMIF(Valuation!$B$5:$B$417,$A13,Valuation!$M$5:$M$417) | D13: =SUMIF(Valuation!$B$5:$B$417,$A13,Valuation!$N$5:$N$417) | E13: =D13-C13
A14: TOTAL | B14: =SUM(B5:B13) | C14: =SUM(C5:C13) | D14: =SUM(D5:D13) | E14: =SUM(E5:E13)
A17: How each quantity was established
A18: Each item takes its most recent physical count across the source sessions. A line that nobody counted in either session falls back to the quantity the system expected.
A19: Quantity basis | B19: Lines | C19: Value at current prices | D19: % of total
A20: Physically counted 2026-07-31 | B20: =COUNTIF(Valuation!$E$5:$E$417,$A20) | C20: =SUMIF(Valuation!$E$5:$E$417,$A20,Valuation!$N$5:$N$417) | D20: =IF($C$23=0,0,C20/$C$23)
A21: Physically counted 2026-08-01 | B21: =COUNTIF(Valuation!$E$5:$E$417,$A21) | C21: =SUMIF(Valuation!$E$5:$E$417,$A21,Valuation!$N$5:$N$417) | D21: =IF($C$23=0,0,C21/$C$23)
A22: Skipped — expected qty at 2026-08-01 | B22: =COUNTIF(Valuation!$E$5:$E$417,$A22) | C22: =SUMIF(Valuation!$E$5:$E$417,$A22,Valuation!$N$5:$N$417) | D22: =IF($C$23=0,0,C22/$C$23)
A23: TOTAL | B23: =SUM(B20:B22) | C23: =SUM(C20:C22)

Sheet Notes
A1: Basis of preparation
A3: Scope. Revenue centre KITCHEN, which is the default revenue centre — its stock is held on the inventory record itself rather than as a per-centre allocation. 413 items.
A5: Quantities. The month-end was counted across two sessions: Prep count July 31 (2026-07-31) + Full Count End of Month (2026-08-01). Neither session on its own holds the whole position, because the items counted in one appear in the other as carried-forward lines. Each item is therefore shown at its MOST RECENT PHYSICAL count, and the Counted on column says which date that was (2026-07-31: 48 items, 2026-08-01: 365 items). 412 of 413 lines rest on a physical observation.
A7: Quantities are shown both in the unit the counter worked in (Qty counted / Count unit) and in the item's base unit, which is what the system stores and what the valuation multiplies. Base quantities are the figures the count itself recorded; pack formats have been repaired since, and re-deriving a counter's entry through a corrected pack would answer a different question than the one they answered on the night.
A9: Prices. The count froze a price against each line when it was finalized. Several of those prices were subsequently found to be wrong: when a supplier changed pack size, the new case price was divided by the item's old pack size, so the cost was wrong by the ratio between them. Those items have since been corrected. This workbook values the counted quantities at the CORRECTED prices and shows the price used at count time alongside, so the restatement of each line is visible. The difference is in the Change column and is subtotalled by category on the Summary sheet.
A11: Comparatives. Counts before 30 June 2026 are not comparable with this one. Eighteen items were priced at zero in the 1 June count and eleven more at under $0.002 per base unit, and fourteen items have changed unit basis since (for example Yellow potato from each to grams), so their quantities do not line up either. The 1 June count reported $17,670; those same counted quantities at 30 June prices come to $26,942. Any trend drawn across that date reflects the repricing, not a change in stock.
A13: Items subsequently deactivated remain in this valuation, because they were on hand at the count date.
A15: Formulas. Value columns are formulas over the quantity and price columns, so correcting a price in this workbook updates the totals. Nothing is a pasted result.
A17: Check figures. The value columns are live formulas, so Excel computes them when this file opens. They should total $24,945.95 at count prices and $24,784.62 at current prices, a change of $-161.32. If the totals differ from these figures, a price has been edited since this file was produced.
A19: Source count session ids: 9ed49415-66c9-441d-a182-17bf941562fc, 33adf80a-0660-4114-b150-d010164afc51
A20: Position as at: 2026-08-01
A21: Prices as at: 2026-08-11 06:34:18 UTC
